prikfy/__init__.py
prikfy/custom_exception.py
prikfy/logger.py
prikfy/transform/__init__.py
prikfy/utils/__init__.py
prikfy/utils/data.py
prikfy/utils/helpers.py
prikfy/utils/operation/__init__.py
prikfy/utils/operation/number_to_word.py
prikfy-0.0.3.dist-info/LICENSE
prikfy-0.0.3.dist-info/METADATA
prikfy-0.0.3.dist-info/WHEEL
prikfy-0.0.3.dist-info/top_level.txt
prikfy-0.0.3.dist-info/RECORD
