Metadata-Version: 2.1
Name: prikfy
Version: 0.0.3
Summary: A small python package
Home-page: http://github.com/Prikshit7766/prikfy
Author: Prikshit7766
Author-email: prikshitsharma8024@gmail.com
License: MIT
Project-URL: Bug Tracker, http://github.com/Prikshit7766/prikfy/issues
Classifier: Programming Language :: Python :: 3.7
Classifier: Programming Language :: Python :: 3.8
Classifier: Programming Language :: Python :: 3.9
Classifier: Operating System :: OS Independent
Requires-Python: >=3.7
License-File: LICENSE
